QuestionsParser
