Metadata-Version: 2.1
Name: QuestionsParser
Version: 1.0.1
Summary: A Python package for parsing questions from pdf files.
Author: Andrew Yaroshevych
Author-email: ayaroshlvua@gmail.com
License: UNKNOWN
Project-URL: Source Code, https://github.com/andylvua/QuestionsParser
Platform: UNKNOWN
Classifier: Programming Language :: Python :: 3
Classifier: License :: OSI Approved :: MIT License
Classifier: Operating System :: OS Independent
License-File: LICENSE
